[
  {
    "region": "Australia",
    "city": "Melbourne",
    "name": "Bourke Street",
    "address": "152 Elizabeth Street, Melbourne VIC 3000"
  },
  {
    "region": "Australia",
    "city": "Melbourne",
    "name": "Collins Street",
    "address": "401 Collins Street, Melbourne VIC 3000"
  },
  {
    "region": "Australia",
    "city": "Sydney",
    "name": "333 George Street",
    "address": "333 George Street, Sydney NSW 2000"
  },
  {
    "region": "Australia",
    "city": "Sydney",
    "name": "Pyrmont",
    "address": "100 Harris St, Sydney NSW 2009"
  },
  {
    "region": "Australia",
    "city": "Sydney",
    "name": "Martin Place",
    "address": "5 Martin Place, Sydney NSW 2000"
  },
  {
    "region": "Canada",
    "city": "Montreal",
    "name": "L'Avenue",
    "address": "1275 Avenue des Canadiens-de-Montréal, Montreal QC H3B 0G4"
  },
  {
    "region": "Canada",
    "city": "Montreal",
    "name": "Place Ville Marie",
    "address": "3 Place Ville Marie, Montreal QC H3B 2E3"
  },
  {
    "region": "Canada",
    "city": "Toronto",
    "name": "33 Bloor Street",
    "address": "33 Bloor , Toronto ON M4W 3H1"
  },
  {
    "region": "Canada",
    "city": "Toronto",
    "name": "Richmond Street West",
    "address": "240 Richmond Street W, Toronto ON M5V 1V6"
  },
  {
    "region": "Canada",
    "city": "Vancouver",
    "name": "Burrard Station",
    "address": "595 Burrard St, Vancouver BC V7X 1L4"
  },
  {
    "region": "Canada",
    "city": "Vancouver",
    "name": "555 Burrard Street",
    "address": "555 Burrard St, Vancouver BC V7X 1M8"
  },
  {
    "region": "China",
    "city": "Beijing",
    "name": "Digital Media Building",
    "address": "7 Xinxi Rd, Beijing 11 100085"
  },
  {
    "region": "China",
    "city": "Beijing",
    "name": "Ciyunsi",
    "address": "6th FL, Tower A Sino Ocean International Center, 56 East 4th Ring Road Middle , Beijing 11 100025"
  },
  {
    "region": "China",
    "city": "Beijing",
    "name": "Sanlitun",
    "address": "North Taikoo Li, 11 Sanlitun Road, TWR N3, Beijing 11 100027"
  },
  {
    "region": "China",
    "city": "Beijing",
    "name": "Beijing FUN",
    "address": "No. 19 Langfangtoutiao, Beijing 11 100051"
  },
  {
    "region": "China",
    "city": "Beijing",
    "name": "Guomao",
    "address": "112 Jianguo Road, Beijing 11 100000"
  },
  {
    "region": "China",
    "city": "Beijing",
    "name": "Guanghua Lu",
    "address": "7th FL, Tower AB Office Park, 10 Jintong West Road, Beijing 11 100020"
  },
  {
    "region": "China",
    "city": "Beijing",
    "name": "Wangjing",
    "address": "16 South Guangshun Street, Donghuang Building 17th Floor, Beijing 11 100015"
  },
  {
    "region": "China",
    "city": "Hong Kong",
    "name": "Standard Chartered Tower",
    "address": "388 Kwun Tong Rd, Hong Kong"
  },
  {
    "region": "China",
    "city": "Hong Kong",
    "name": "Wan Chai",
    "address": "10F Mass Mutual Tower, 33 Lockhart Road, Hong Kong"
  },
  {
    "region": "China",
    "city": "Hong Kong",
    "name": "Cityplaza Three",
    "address": "Cityplaza Three, Hong Kong HK"
  },
  {
    "region": "China",
    "city": "Hong Kong",
    "name": "Tower 535",
    "address": "20/F Tower 535, 535 Jaffe Road, Hong Kong"
  },
  {
    "region": "China",
    "city": "Shanghai",
    "name": "Yunnan Lu",
    "address": "The Konnect, No. 118 South Yunnan Road, Shanghai 31 200010"
  },
  {
    "region": "China",
    "city": "Shanghai",
    "name": "Yan'an Dong Lu",
    "address": "588 Yan'an East Road, Shanghai 31 200000"
  },
  {
    "region": "China",
    "city": "Shanghai",
    "name": "Nanjing Xi Lu",
    "address": "819 West Nanjing Road, Shanghai 31 200001"
  },
  {
    "region": "China",
    "city": "Shanghai",
    "name": "Xujiahui",
    "address": "No. 1901 Huashan Lu, Shanghai 31 200030"
  },
  {
    "region": "China",
    "city": "Shanghai",
    "name": "Huai Hai Zhong Lu",
    "address": "627 Huaihai Middle Rd, Shanghai 31 200000"
  },
  {
    "region": "China",
    "city": "Shanghai",
    "name": "Weihai Lu",
    "address": "696 Weihai Road, Shanghai 31 200041"
  },
  {
    "region": "China",
    "city": "Shanghai",
    "name": "Financial Center",
    "address": "15F, HSBC Building, Shanghai ifc, Shanghai 31 200120"
  },
  {
    "region": "China",
    "city": "Shanghai",
    "name": "Huamu Lu",
    "address": "1155 Fangdian Road, Pudong, Shanghai 31 201203"
  },
  {
    "region": "China",
    "city": "Shanghai",
    "name": "Yanping Lu",
    "address": "135 Yanping Road, Shanghai 31 200042"
  },
  {
    "region": "China",
    "city": "Shanghai",
    "name": "Dalian Lu",
    "address": "500 Dalian Rd, Shanghai 31 200082"
  },
  {
    "region": "Europe",
    "city": "Amsterdam",
    "name": "Strawinskylaan",
    "address": "Strawinskylaan 3101, Amsterdam 1077 ZX"
  },
  {
    "region": "Europe",
    "city": "Amsterdam",
    "name": "Weteringschans",
    "address": "Weteringschans 165 C, Amsterdam 1017XD"
  },
  {
    "region": "Europe",
    "city": "Amsterdam",
    "name": "Metropool",
    "address": "Weesperstraat 61-105, Amsterdam 1018VN"
  },
  {
    "region": "Europe",
    "city": "Barcelona",
    "name": "Glories",
    "address": "Luxa, Barcelona B 08018"
  },
  {
    "region": "Europe",
    "city": "Berlin",
    "name": "Ku'damm",
    "address": "Kurfürstendamm 11, Berlin BE 10719"
  },
  {
    "region": "Europe",
    "city": "Berlin",
    "name": "Atrium Tower",
    "address": "Eichhornstraße 3, Berlin 10785"
  },
  {
    "region": "Europe",
    "city": "Berlin",
    "name": "Hackescher Markt",
    "address": "Neue Schônhauserstraße 3-5, Berlin 10178"
  },
  {
    "region": "Europe",
    "city": "Berlin",
    "name": "Sony Center",
    "address": "Potsdamer Platz - Kemperplatz 1, Berlin 10785"
  },
  {
    "region": "Europe",
    "city": "Berlin",
    "name": "Potsdamer Platz",
    "address": "Stresemannstraße 123, Berlin 10963"
  },
  {
    "region": "Europe",
    "city": "Dublin",
    "name": "Iveagh Court",
    "address": "Block D, Iveagh Court, Dublin D02"
  },
  {
    "region": "Europe",
    "city": "Frankfurt",
    "name": "Goetheplatz",
    "address": "Neue Rothofstr. 13-19, Frankfurt HE 60313"
  },
  {
    "region": "Europe",
    "city": "Hamburg",
    "name": "Stadthaus",
    "address": "Axel-Springer-Platz 3, Hamburg 20355"
  },
  {
    "region": "Europe",
    "city": "London",
    "name": "Chancery Lane - The Cursitor",
    "address": "38 Chancery Lane, London WC2A 1EN"
  },
  {
    "region": "Europe",
    "city": "London",
    "name": "Old St.",
    "address": "41 Corsham Street, London N1 6DR"
  },
  {
    "region": "Europe",
    "city": "London",
    "name": "Tower Bridge",
    "address": "1 St. Katharine's Way, London E1W 1UN"
  },
  {
    "region": "Europe",
    "city": "London",
    "name": "Soho - Sheraton House",
    "address": "16 Great Chapel St, London W1F 8FL"
  },
  {
    "region": "Europe",
    "city": "London",
    "name": "Marylebone - North West House",
    "address": "119 Marylebone Road, London NW1 5PU"
  },
  {
    "region": "Europe",
    "city": "London",
    "name": "South Bank",
    "address": "22 Upper Ground, London SE1 9PD"
  },
  {
    "region": "Europe",
    "city": "London",
    "name": "Mansion House",
    "address": "33 Queen St, London EC4R 1AP"
  },
  {
    "region": "Europe",
    "city": "London",
    "name": "131 Finsbury Pavement",
    "address": "131 Finsbury Pavement, London EC2A 1NT"
  },
  {
    "region": "Europe",
    "city": "London",
    "name": "Spitalfields",
    "address": "1 Primrose Street, London EC2A 2EX"
  },
  {
    "region": "Europe",
    "city": "London",
    "name": "Kings Place",
    "address": "90 York Way, London N1 9AG"
  },
  {
    "region": "Europe",
    "city": "London",
    "name": "Paddington",
    "address": "2 Eastbourne Terrace, London W2 6LG"
  },
  {
    "region": "Europe",
    "city": "London",
    "name": "Moorgate",
    "address": "1 Fore Street Avenue, London EC2Y 9DT"
  },
  {
    "region": "Europe",
    "city": "London",
    "name": "South Bank Central",
    "address": "30 Stamford Street, London SE1 9PY"
  },
  {
    "region": "Europe",
    "city": "London",
    "name": "Chancery Lane: Fox Court",
    "address": "14 Gray's Inn Road, London WC1X 8HN"
  },
  {
    "region": "Europe",
    "city": "London",
    "name": "Waterhouse Square",
    "address": "138 Holborn, London EC1N 2SW"
  },
  {
    "region": "Europe",
    "city": "London",
    "name": "Aldwych House",
    "address": "71-91 Aldwych, London WC2B 4HN"
  },
  {
    "region": "Europe",
    "city": "London",
    "name": "Soho - Medius House",
    "address": "2 Sheraton St, London W1F 8BH"
  },
  {
    "region": "Europe",
    "city": "London",
    "name": "Hammersmith Grove",
    "address": "12 Hammersmith Grove, London W6 7AP"
  },
  {
    "region": "Europe",
    "city": "London",
    "name": "Devonshire Square",
    "address": "9 Devonshire Square, London EC2M 4YD"
  },
  {
    "region": "Europe",
    "city": "London",
    "name": "London Fields",
    "address": "115 Mare Street, London UK E8 4RU"
  },
  {
    "region": "Europe",
    "city": "London",
    "name": "Hoxton",
    "address": "97 Hackney Rd, London E2 8ET"
  },
  {
    "region": "Europe",
    "city": "London",
    "name": "Hammersmith: Brook Green",
    "address": "Shepherds Bush Road, London W6 7NL"
  },
  {
    "region": "Europe",
    "city": "London",
    "name": "Aldgate Tower",
    "address": "Aldgate Tower, London E1 8FA"
  },
  {
    "region": "Europe",
    "city": "London",
    "name": "Shoreditch Mark Square",
    "address": "1 Mark Square , London EC2A 4EG"
  },
  {
    "region": "Europe",
    "city": "London",
    "name": "Bishopsgate",
    "address": "15 Bishopsgate, London EC2N 3AR"
  },
  {
    "region": "Europe",
    "city": "Madrid",
    "name": "Paseo De La Castellana 77",
    "address": "Paseo de la Castellana 77, Madrid M 28046"
  },
  {
    "region": "Europe",
    "city": "Madrid",
    "name": "Castellana 43",
    "address": "Paseo de la Castellana, 43, Madrid M 28046"
  },
  {
    "region": "Europe",
    "city": "Manchester",
    "name": "1 St Peter's Square",
    "address": "1 St Peter's Square, Manchester MAN M2 3AE"
  },
  {
    "region": "Europe",
    "city": "Manchester",
    "name": "No. 1 Spinningfields",
    "address": "Quay Street, Manchester MAN M3 3JE"
  },
  {
    "region": "Europe",
    "city": "Munich",
    "name": "Oskar Von Miller",
    "address": "20 Oskar-von-Miller-Ring, Munich BY 80333"
  },
  {
    "region": "Europe",
    "city": "Paris",
    "name": "Coeur Marais",
    "address": "64-66 Rue Des Archives, Paris 75 75003"
  },
  {
    "region": "Europe",
    "city": "Paris",
    "name": "La Fayette",
    "address": "33 Rue La Fayette, Paris 75 75009"
  },
  {
    "region": "Europe",
    "city": "Paris",
    "name": "92 Champs-Élysées",
    "address": "92 avenue des Champs-Élysées, Paris 75 75008"
  },
  {
    "region": "Europe",
    "city": "Paris",
    "name": "Colisée",
    "address": "40 rue du Colisée, Paris 75 75008"
  },
  {
    "region": "India",
    "city": "Bengaluru",
    "name": "EGL",
    "address": "Embassy Golf Links, Cinnabar Hills, Bengaluru KA 560071"
  },
  {
    "region": "India",
    "city": "Bengaluru",
    "name": "Koramangala",
    "address": "Prestige Atlanta 80 Feet Main Road, Bengaluru KA 560034"
  },
  {
    "region": "India",
    "city": "Bengaluru",
    "name": "Hebbal",
    "address": "9th Floor, RMZ Latitude Commercial, Bellary Rd, Hebbal, Near Godrej Apt, Bengaluru KA 560024"
  },
  {
    "region": "India",
    "city": "Bengaluru",
    "name": "Galaxy",
    "address": "43 Residency Rd, Bengaluru KA 560025"
  },
  {
    "region": "India",
    "city": "Mumbai",
    "name": "Marol",
    "address": "The Masterpiece, Marol Metro Station, Mumbai MH 400059"
  },
  {
    "region": "India",
    "city": "Mumbai",
    "name": "BKC",
    "address": "C-20, G Block, Bandra-Kurla Complex, Mumbai MH 400051"
  },
  {
    "region": "India",
    "city": "Mumbai",
    "name": "Vikhroli West",
    "address": "13th Floor, 247 Park, Hindustan C. Bus Stop, Lal Bahadur Shastri Rd, Gandhi Nagar, Vikhroli West, Mumbai MH 400079"
  },
  {
    "region": "India",
    "city": "Mumbai",
    "name": "Oberoi Commerz II",
    "address": "20th Floor, Oberoi Commerz II, International Business Park, Oberoi Garden City, off Western Express Highway, Goregaon (East), Mumbai MH 400063"
  },
  {
    "region": "India",
    "city": "NCR",
    "name": "Bristol Chowk",
    "address": "Platina Tower, Gurugram HR 122001"
  },
  {
    "region": "Indonesia",
    "city": "Jakarta",
    "name": "Gama Tower",
    "address": "Jalan HR. Rasuna Said Kav. C22, Jakarta JK 12940"
  },
  {
    "region": "Israel",
    "city": "Be'er Sheva",
    "name": "Be'er Sheva",
    "address": "Gev Yam Negev Park, Be'er Sheva 84709"
  },
  {
    "region": "Israel",
    "city": "Herzliya",
    "name": "Herzliya",
    "address": "1 Shankar St, Herzliya 4672501"
  },
  {
    "region": "Israel",
    "city": "Tel Aviv",
    "name": "Dubnov",
    "address": "7 Dubnov, Tel Aviv 6473207"
  },
  {
    "region": "Israel",
    "city": "Tel Aviv",
    "name": "Ibn Gabirol",
    "address": "30 Ibn Gabirol, Tel Aviv 6407807"
  },
  {
    "region": "Israel",
    "city": "Tel Aviv",
    "name": "Menachem Begin 144",
    "address": "Derech Menachem Begin 144, Tel Aviv 6492102"
  },
  {
    "region": "Israel",
    "city": "Tel Aviv",
    "name": "Sarona",
    "address": "3 Aluf Kalman Magen, Tel Aviv 6107075"
  },
  {
    "region": "Israel",
    "city": "Tel Aviv",
    "name": "HaZerem",
    "address": "7 HaPelech Street, Tel Aviv 6816727"
  },
  {
    "region": "Japan",
    "city": "Tokyo",
    "name": "Ark Hills South",
    "address": "1-4-5 Roppongi, Tokyo 13 106-0032"
  },
  {
    "region": "Japan",
    "city": "Tokyo",
    "name": "Hibiya Park Front",
    "address": "2-1-6 Uchisaiwaicho, Chiyoda-ku, Tokyo 13 100-0011"
  },
  {
    "region": "Japan",
    "city": "Tokyo",
    "name": "Shimbashi",
    "address": "6-19-13 Shimbashi, Tokyo 13 105-0004"
  },
  {
    "region": "Japan",
    "city": "Tokyo",
    "name": "Ginza Six",
    "address": "6-10-1 Ginza, Tokyo 13 104-0061"
  },
  {
    "region": "Japan",
    "city": "Tokyo",
    "name": "Iceberg",
    "address": "6-12-18 Jingumae, Tokyo 13 150-0001"
  },
  {
    "region": "Japan",
    "city": "Tokyo",
    "name": "Marunouchi Kitaguchi",
    "address": "1-6-5 Marunouchi, Tokyo 13 100-0005"
  },
  {
    "region": "Latin America",
    "city": "Bogota",
    "name": "La 93",
    "address": "Calle 93 #19-55, Bogota DC 110221"
  },
  {
    "region": "Latin America",
    "city": "Bogota",
    "name": "Usaquén",
    "address": "Carrera 7 # 116-50, Bogota DC"
  },
  {
    "region": "Latin America",
    "city": "Buenos Aires",
    "name": "Libertador 1000",
    "address": "Av. Del Libertador 1000, Vicente López, Buenos Aires B1638BEV"
  },
  {
    "region": "Latin America",
    "city": "Buenos Aires",
    "name": "Torre Bellini",
    "address": "Esmeralda 950, Buenos Aires B C1007"
  },
  {
    "region": "Latin America",
    "city": "Lima",
    "name": "Real 2",
    "address": "Av. Victor Andrés Belaúnde 147,Via Principal 133, , Lima LIM"
  },
  {
    "region": "Latin America",
    "city": "Mexico City",
    "name": "Park Plaza",
    "address": "Av. Javier Barros Sierra 495, Mexico City DIF 01376"
  },
  {
    "region": "Latin America",
    "city": "Mexico City",
    "name": "Cervantes",
    "address": "Blvd. Miguel de Cervantes Saavedra 169, Mexico City CMX 11520"
  },
  {
    "region": "Latin America",
    "city": "Mexico City",
    "name": "Varsovia",
    "address": "Varsovia 36, Mexico City DIF 06600"
  },
  {
    "region": "Latin America",
    "city": "Mexico City",
    "name": "Insurgentes Sur 601",
    "address": "Av. de los Insurgentes 601, Mexico City DIF 3810"
  },
  {
    "region": "Latin America",
    "city": "Mexico City",
    "name": "Arcos Bosques",
    "address": "Paseo De Los Tamarindos 90, Mexico City DIF 05120"
  },
  {
    "region": "Latin America",
    "city": "Mexico City",
    "name": "Reforma Latino",
    "address": "Paseo de la Reforma 296, Mexico City DIF 06600"
  },
  {
    "region": "Latin America",
    "city": "Mexico City",
    "name": "Montes Urales",
    "address": "Montes Urales 424, Lomas - Virreyes, Mexico City DIF 11000"
  },
  {
    "region": "Latin America",
    "city": "Mexico City",
    "name": "Artz Pedregal",
    "address": "Blvd. Adolfo Ruiz Cortines 3720, Mexico City CMX 01900"
  },
  {
    "region": "Latin America",
    "city": "Rio de Janeiro",
    "name": "Ipanema",
    "address": "495 Visconde de Piraja Avenue, Rio de Janeiro RJ 22410-002"
  },
  {
    "region": "Latin America",
    "city": "Rio de Janeiro",
    "name": "Carioca",
    "address": "Avenida Almirante Barroso, 81, Rio de Janeiro RJ 20031-004"
  },
  {
    "region": "Latin America",
    "city": "Sao Paulo",
    "name": "Berrini",
    "address": "Av. das Nações Unidas, São Paulo SP 04578-910"
  },
  {
    "region": "Latin America",
    "city": "Sao Paulo",
    "name": "Faria Lima",
    "address": "Rua Prof. Atílio Innocenti, São Paulo SP 04538-000"
  },
  {
    "region": "Latin America",
    "city": "Sao Paulo",
    "name": "habitat",
    "address": "Avenida Angélica, São Paulo SP 01153-000"
  },
  {
    "region": "Latin America",
    "city": "Sao Paulo",
    "name": "Av. Das Nações Unidas 14261",
    "address": "Av. das Nações Unidas, São Paulo SP 04533-085"
  },
  {
    "region": "Latin America",
    "city": "Sao Paulo",
    "name": "Torre JK",
    "address": "Av. Presidente Juscelino Kubitschek, São Paulo SP 04543-011"
  },
  {
    "region": "Latin America",
    "city": "Sao Paulo",
    "name": "Paulista",
    "address": "Av. Paulista, São Paulo SP 01310-100"
  },
  {
    "region": "Singapore",
    "city": "Singapore",
    "name": "Spacemob Ascent",
    "address": "2 Science Park Drive, Singapore 118222"
  },
  {
    "region": "Singapore",
    "city": "Singapore",
    "name": "60 Anson Road",
    "address": "60 Anson Road, Singapore 079914"
  },
  {
    "region": "Singapore",
    "city": "Singapore",
    "name": "Spacemob Claymore",
    "address": "8 Claymore Hill, Singapore 229572"
  },
  {
    "region": "Singapore",
    "city": "Singapore",
    "name": "22 Cross Street",
    "address": "22 Cross Street, Singapore 048421"
  },
  {
    "region": "Singapore",
    "city": "Singapore",
    "name": "71 Robinson",
    "address": "71 Robinson Road, Singapore 068895"
  },
  {
    "region": "Singapore",
    "city": "Singapore",
    "name": "Beach Centre",
    "address": "15 Beach Road, 2nd Floor , Singapore 189677"
  },
  {
    "region": "Singapore",
    "city": "Singapore",
    "name": "8 Cross Street",
    "address": "8 Cross Street, Singapore 048424"
  },
  {
    "region": "South Korea",
    "city": "Seoul",
    "name": "Seolleung Station",
    "address": "302, Teheran-ro, Seoul 11 06210"
  },
  {
    "region": "South Korea",
    "city": "Seoul",
    "name": "Yeoksam Station II",
    "address": "14, Teheran-ro 26-gil, Seoul 11 06236"
  },
  {
    "region": "South Korea",
    "city": "Seoul",
    "name": "Euljiro",
    "address": "343, Samil-daero, Seoul"
  },
  {
    "region": "South Korea",
    "city": "Seoul",
    "name": "Gangnam Station",
    "address": "373 Gangnam-daero, Seoul"
  },
  {
    "region": "South Korea",
    "city": "Seoul",
    "name": "Gwanghwamun",
    "address": "50 Jong-ro 1-gil, Seoul 03142"
  },
  {
    "region": "South Korea",
    "city": "Seoul",
    "name": "Samseong Station",
    "address": "507 Teheran-ro, Seoul 11"
  },
  {
    "region": "South Korea",
    "city": "Seoul",
    "name": "Yeoksam Station",
    "address": "142 Teheran-ro, Seoul 06236"
  },
  {
    "region": "South Korea",
    "city": "Seoul",
    "name": "Yeouido Station",
    "address": "83, Uisadaing-daero, Yeongdeungpo-gu, Seoul 11 07325"
  },
  {
    "region": "South Korea",
    "city": "Seoul",
    "name": "Seoul Station",
    "address": "416 Hangang-Daero Jung-gu , Seoul 11 04637"
  },
  {
    "region": "US",
    "city": "Atlanta",
    "name": "1372 Peachtree",
    "address": "1372 Peachtree St, Atlanta GA 30309"
  },
  {
    "region": "US",
    "city": "Atlanta",
    "name": "Tower Place",
    "address": "3340 Peachtree Rd NE, Atlanta GA 30326"
  },
  {
    "region": "US",
    "city": "Atlanta",
    "name": "Terminus",
    "address": "3280 Peachtree Road NE, Atlanta GA 30305"
  },
  {
    "region": "US",
    "city": "Atlanta",
    "name": "Colony Square",
    "address": "1175 Peachtree St NE, Atlanta GA 30361"
  },
  {
    "region": "US",
    "city": "Austin",
    "name": "801 Barton Springs",
    "address": "801 Barton Springs, Austin TX 78704"
  },
  {
    "region": "US",
    "city": "Austin",
    "name": "Congress",
    "address": "600 Congress Ave, Austin TX 78701"
  },
  {
    "region": "US",
    "city": "Austin",
    "name": "Domain",
    "address": "11801 Domain Blvd, Austin TX 78758"
  },
  {
    "region": "US",
    "city": "Austin",
    "name": "University Park",
    "address": "3300 N Interstate 35, Austin TX 78705"
  },
  {
    "region": "US",
    "city": "Austin",
    "name": "West 6th",
    "address": "221 West 6th Street, Austin TX 78701"
  },
  {
    "region": "US",
    "city": "Bay Area",
    "name": "Spear Street",
    "address": "201 Spear St, San Francisco CA 94105"
  },
  {
    "region": "US",
    "city": "Bay Area",
    "name": "SOMA",
    "address": "156 2nd Street, San Francisco CA 94105"
  },
  {
    "region": "US",
    "city": "Bay Area",
    "name": "Berkeley",
    "address": "2120 University Ave, Berkeley CA 94704"
  },
  {
    "region": "US",
    "city": "Bay Area",
    "name": "650 California Street",
    "address": "650 California Street, San Francisco CA 94108"
  },
  {
    "region": "US",
    "city": "Bay Area",
    "name": "City Center",
    "address": "1111 Broadway, Oakland CA 94607"
  },
  {
    "region": "US",
    "city": "Bay Area",
    "name": "Montgomery Station",
    "address": "44 Montgomery St, San Francisco CA 94104"
  },
  {
    "region": "US",
    "city": "Bay Area",
    "name": "Transbay",
    "address": "535 Mission St, San Francisco CA 94105"
  },
  {
    "region": "US",
    "city": "Bay Area",
    "name": "600 California Street",
    "address": "600 California Street, San Francisco CA 94108"
  },
  {
    "region": "US",
    "city": "Bay Area",
    "name": "Embarcadero Center",
    "address": "2 Embarcadero Center, San Francisco CA 94111"
  },
  {
    "region": "US",
    "city": "Bay Area",
    "name": "Mid-Market",
    "address": "995 Market St, San Francisco CA 94103"
  },
  {
    "region": "US",
    "city": "Bay Area",
    "name": "Civic Center",
    "address": "1161 Mission St, San Francisco CA 94103"
  },
  {
    "region": "US",
    "city": "Bay Area",
    "name": "Jackson Square",
    "address": "655 Montgomery Street, San Francisco CA 94111"
  },
  {
    "region": "US",
    "city": "Bay Area",
    "name": "Golden Gate",
    "address": "25 Taylor Street, San Francisco CA 94102"
  },
  {
    "region": "US",
    "city": "Bay Area",
    "name": "Valley Towers",
    "address": "75 E Santa Clara Street, San Jose CA 95113"
  },
  {
    "region": "US",
    "city": "Boston",
    "name": "Fort Point",
    "address": "51 Melcher St, Boston MA 02210"
  },
  {
    "region": "US",
    "city": "Boston",
    "name": "Mass Ave.",
    "address": "625 Massachusetts Ave, Cambridge MA 02139"
  },
  {
    "region": "US",
    "city": "Boston",
    "name": "One Beacon Street",
    "address": "1 Beacon St, Boston MA 02108"
  },
  {
    "region": "US",
    "city": "Boston",
    "name": "St. James",
    "address": "31 St. James Ave 6th Fl, Boston MA 02116"
  },
  {
    "region": "US",
    "city": "Boston",
    "name": "200 Portland",
    "address": "200 Portland St, Boston MA 02114"
  },
  {
    "region": "US",
    "city": "Boston",
    "name": "South Station",
    "address": "745 Atlantic Ave, Boston MA 02111"
  },
  {
    "region": "US",
    "city": "Charlotte",
    "name": "Stonewall Station",
    "address": "615 S College St, Charlotte NC 28202"
  },
  {
    "region": "US",
    "city": "Charlotte",
    "name": "128 S Tryon St",
    "address": "128 South Tryon St, Charlotte NC 28202"
  },
  {
    "region": "US",
    "city": "Chicago",
    "name": "Grant Park",
    "address": "332 S Michigan Ave, Chicago IL 60604"
  },
  {
    "region": "US",
    "city": "Chicago",
    "name": "National Building",
    "address": "125 S Clark Street, Chicago IL 60603"
  },
  {
    "region": "US",
    "city": "Chicago",
    "name": "River North",
    "address": "111 W Illinois St, Chicago IL 60654"
  },
  {
    "region": "US",
    "city": "Chicago",
    "name": "Kinzie",
    "address": "20 West Kinzie Street, Chicago IL 60654"
  },
  {
    "region": "US",
    "city": "Chicago",
    "name": "Fulton Market",
    "address": "220 N Green St, Chicago IL 60607"
  },
  {
    "region": "US",
    "city": "Chicago",
    "name": "State Street",
    "address": "100 S State Street, Chicago IL 60603"
  },
  {
    "region": "US",
    "city": "Dallas",
    "name": "Thanksgiving Tower",
    "address": "1601 Elm St, Dallas TX 75201"
  },
  {
    "region": "US",
    "city": "Dallas",
    "name": "Uptown",
    "address": "1920 McKinney Ave, Dallas TX 75201"
  },
  {
    "region": "US",
    "city": "Dallas",
    "name": "Clearfork",
    "address": "5049 Edwards Ranch, Fort Worth TX 76109"
  },
  {
    "region": "US",
    "city": "Dallas",
    "name": "Legacy West",
    "address": "7700 Windrose, Plano TX 75024"
  },
  {
    "region": "US",
    "city": "Denver",
    "name": "Union Station",
    "address": "1550 Wewatta St, Denver CO 80202"
  },
  {
    "region": "US",
    "city": "Denver",
    "name": "LoHi",
    "address": "2420 17th St, Denver CO 80202"
  },
  {
    "region": "US",
    "city": "Denver",
    "name": "Larimer Square",
    "address": "1144 15th Street, Denver CO 80202"
  },
  {
    "region": "US",
    "city": "Detroit",
    "name": "Campus Martius",
    "address": "1001 Woodward Ave, Detroit MI 48226"
  },
  {
    "region": "US",
    "city": "Detroit",
    "name": "Merchant's Row",
    "address": "1449 Woodward Ave., Detroit MI 48226"
  },
  {
    "region": "US",
    "city": "Houston",
    "name": "708 Main Street",
    "address": "708 Main, Houston TX 77002"
  },
  {
    "region": "US",
    "city": "Houston",
    "name": "Houston Galleria",
    "address": "2700 Post Oak Blvd, Houston TX 77056"
  },
  {
    "region": "US",
    "city": "Kansas City",
    "name": "Corrigan Station",
    "address": "1828 Walnut St, 3rd Floor, Kansas City MO 64108"
  },
  {
    "region": "US",
    "city": "Los Angeles",
    "name": "Burbank",
    "address": "3900 W Alameda Ave, Burbank CA 91505"
  },
  {
    "region": "US",
    "city": "Los Angeles",
    "name": "Long Beach",
    "address": "100 W Broadway, Long Beach CA 90802"
  },
  {
    "region": "US",
    "city": "Los Angeles",
    "name": "Culver City",
    "address": "5792 West Jefferson Blvd, Los Angeles CA 90016"
  },
  {
    "region": "US",
    "city": "Los Angeles",
    "name": "Santa Monica",
    "address": "520 Broadway, Santa Monica CA 90401"
  },
  {
    "region": "US",
    "city": "Los Angeles",
    "name": "Vine",
    "address": "1601 Vine Street, Los Angeles CA 90028"
  },
  {
    "region": "US",
    "city": "Los Angeles",
    "name": "Playa Vista",
    "address": "12655 W. Jefferson Blvd, Los Angeles CA 90066"
  },
  {
    "region": "US",
    "city": "Los Angeles",
    "name": "Pasadena",
    "address": "177 E Colorado Blvd, Pasadena CA 91105"
  },
  {
    "region": "US",
    "city": "Los Angeles",
    "name": "Hollywood",
    "address": "7083 Hollywood Boulevard, Los Angeles CA 90028"
  },
  {
    "region": "US",
    "city": "Los Angeles",
    "name": "Fine Arts Building",
    "address": "811 W 7th St, Los Angeles CA 90017"
  },
  {
    "region": "US",
    "city": "Los Angeles",
    "name": "Constellation",
    "address": "10250 Constellation Blvd, Los Angeles CA 90067"
  },
  {
    "region": "US",
    "city": "Los Angeles",
    "name": "Manhattan Beach Towers",
    "address": "1240 Rosecrans Ave #120, Manhattan Beach CA 90266"
  },
  {
    "region": "US",
    "city": "Los Angeles",
    "name": "Gas Tower",
    "address": "555 West 5th Street, 35th Floor, Los Angeles CA 90013"
  },
  {
    "region": "US",
    "city": "Los Angeles",
    "name": "Promenade",
    "address": "312 Arizona Ave, Santa Monica CA 90401"
  },
  {
    "region": "US",
    "city": "Los Angeles",
    "name": "La Brea",
    "address": "925 N La Brea Ave, Los Angeles CA 90038"
  },
  {
    "region": "US",
    "city": "Los Angeles",
    "name": "Pacific Design Center",
    "address": "750 N San Vicente Blvd, Los Angeles CA 90069"
  },
  {
    "region": "US",
    "city": "Miami",
    "name": "Brickell City Centre",
    "address": "78 SW 7th Street, Miami FL 33130"
  },
  {
    "region": "US",
    "city": "Miami",
    "name": "Ponce de Leon",
    "address": "2222 Ponce De Leon Blvd, Miami FL 33134"
  },
  {
    "region": "US",
    "city": "Miami",
    "name": "Security Building",
    "address": "117 NE 1st Ave, Miami FL 33132"
  },
  {
    "region": "US",
    "city": "Miami",
    "name": "Lincoln Road",
    "address": "350 Lincoln Road, Miami Beach FL 33139"
  },
  {
    "region": "US",
    "city": "Miami",
    "name": "South of Fifth",
    "address": "429 Lenox Ave, Miami Beach FL 33139"
  },
  {
    "region": "US",
    "city": "Minneapolis",
    "name": "Capella Tower",
    "address": "225 South 6th St, Minneapolis MN 55402"
  },
  {
    "region": "US",
    "city": "Nashville",
    "name": "One Nashville Place",
    "address": "150 4th Ave N, Nashville TN 37219"
  },
  {
    "region": "US",
    "city": "Nashville",
    "name": "901 Woodland",
    "address": "901 Woodland St, Nashville TN 37206"
  },
  {
    "region": "US",
    "city": "New York City",
    "name": "Meatpacking",
    "address": "1 Little West 12th Street, New York NY 10014"
  },
  {
    "region": "US",
    "city": "New York City",
    "name": "West Broadway",
    "address": "379 West Broadway, New York NY 10012"
  },
  {
    "region": "US",
    "city": "New York City",
    "name": "W. 43rd St.",
    "address": "311 W 43rd St., New York NY 10036"
  },
  {
    "region": "US",
    "city": "New York City",
    "name": "42nd Street",
    "address": "205 E 42nd St, New York NY 10017"
  },
  {
    "region": "US",
    "city": "New York City",
    "name": "E. 57th St.",
    "address": "135 E 57th Street, New York NY 10022"
  },
  {
    "region": "US",
    "city": "New York City",
    "name": "110 Wall St",
    "address": "110 Wall St, New York NY 10005"
  },
  {
    "region": "US",
    "city": "New York City",
    "name": "Chelsea",
    "address": "115 W 18th St, New York NY 10011"
  },
  {
    "region": "US",
    "city": "New York City",
    "name": "Tower 49",
    "address": "12 East 49th Street, New York NY 10017"
  },
  {
    "region": "US",
    "city": "New York City",
    "name": "Dumbo Heights (Sands)",
    "address": "77 Sands St, Brooklyn NY 11201"
  },
  {
    "region": "US",
    "city": "New York City",
    "name": "Soho",
    "address": "154 Grand St., New York NY 10013"
  },
  {
    "region": "US",
    "city": "New York City",
    "name": "Irving Place",
    "address": "33 Irving Pl, New York NY 10003"
  },
  {
    "region": "US",
    "city": "New York City",
    "name": "Times Square",
    "address": "1460 Broadway, New York NY 10036"
  },
  {
    "region": "US",
    "city": "New York City",
    "name": "428 Broadway",
    "address": "428 Broadway, New York NY 10013"
  },
  {
    "region": "US",
    "city": "New York City",
    "name": "Harlem",
    "address": "8 W 126th Street, New York NY 10027"
  },
  {
    "region": "US",
    "city": "New York City",
    "name": "500 7th Avenue",
    "address": "500 7th Avenue, New York NY 10018"
  },
  {
    "region": "US",
    "city": "New York City",
    "name": "30 West 21st Street",
    "address": "30 West 21st Street, New York NY 10010"
  },
  {
    "region": "US",
    "city": "New York City",
    "name": "18 West 18th Street",
    "address": "18 West 18th Street, New York NY 10011"
  },
  {
    "region": "US",
    "city": "New York City",
    "name": "Bryant Park",
    "address": "54 W. 40th St., New York NY 10018"
  },
  {
    "region": "US",
    "city": "New York City",
    "name": "Williamsburg",
    "address": "134 N 4th St., Brooklyn NY 11249"
  },
  {
    "region": "US",
    "city": "New York City",
    "name": "Grand Central",
    "address": "450 Lexington Ave, New York NY 10017"
  },
  {
    "region": "US",
    "city": "New York City",
    "name": "Dumbo Heights (Prospect)",
    "address": "81 Prospect St, Brooklyn NY 11201"
  },
  {
    "region": "US",
    "city": "New York City",
    "name": "575 Fifth",
    "address": "575 5th Ave., New York NY 10017"
  },
  {
    "region": "US",
    "city": "New York City",
    "name": "88 University",
    "address": "88 University Pl, New York NY 10003"
  },
  {
    "region": "US",
    "city": "New York City",
    "name": "Empire State",
    "address": "349 5th Avenue, New York NY 10016"
  },
  {
    "region": "US",
    "city": "New York City",
    "name": "300 Park",
    "address": "300 Park Avenue, New York NY 10022"
  },
  {
    "region": "US",
    "city": "New York City",
    "name": "135 West 41st St.",
    "address": "135 W 41st St, New York NY 10036"
  },
  {
    "region": "US",
    "city": "New York City",
    "name": "Studio Square",
    "address": "3537 36th Street, Astoria NY 11106"
  },
  {
    "region": "US",
    "city": "New York City",
    "name": "205 Hudson",
    "address": "205 Hudson St, New York NY 10013"
  },
  {
    "region": "US",
    "city": "New York City",
    "name": "Fulton Center",
    "address": "200 Broadway, New York NY 10038"
  },
  {
    "region": "US",
    "city": "New York City",
    "name": "524 Broadway",
    "address": "524 Broadway, New York NY 10012"
  },
  {
    "region": "US",
    "city": "New York City",
    "name": "120 E 23rd St",
    "address": "120 E 23rd St, New York NY 10010"
  },
  {
    "region": "US",
    "city": "New York City",
    "name": "115 Broadway",
    "address": "115 Broadway Street, New York NY 10006"
  },
  {
    "region": "US",
    "city": "New York City",
    "name": "125 West 25th Street",
    "address": "125 West 25th Street, New York NY 10001"
  },
  {
    "region": "US",
    "city": "New York City",
    "name": "Montague St.",
    "address": "195 Montague Street, Brooklyn NY 11201"
  },
  {
    "region": "US",
    "city": "New York City",
    "name": "175 Varick St",
    "address": "175 Varick Street, New York NY 10014"
  },
  {
    "region": "US",
    "city": "New York City",
    "name": "404 Fifth Ave",
    "address": "404 5th Ave, New York NY 10018"
  },
  {
    "region": "US",
    "city": "New York City",
    "name": "Queens Plaza",
    "address": "27-01 Queens Plaza N, Long Island City NY 11101"
  },
  {
    "region": "US",
    "city": "New York City",
    "name": "Park South",
    "address": "401 Park Avenue South, New York NY 10016"
  },
  {
    "region": "US",
    "city": "New York City",
    "name": "11 Park Place",
    "address": "11 Park Place, New York NY 10007"
  },
  {
    "region": "US",
    "city": "New York City",
    "name": "Herald Square",
    "address": "950 Sixth Ave, New York NY 10001"
  },
  {
    "region": "US",
    "city": "New York City",
    "name": "W. 57th St.",
    "address": "142 W 57th St, New York NY 10019"
  },
  {
    "region": "US",
    "city": "New York City",
    "name": "79 Madison Ave",
    "address": "79 Madison Ave, New York NY 10016"
  },
  {
    "region": "US",
    "city": "New York City",
    "name": "Penn Station",
    "address": "315 W 36th Street, New York NY 10018"
  },
  {
    "region": "US",
    "city": "New York City",
    "name": "25 Broadway",
    "address": "25 Broadway, New York NY 10004"
  },
  {
    "region": "US",
    "city": "New York City",
    "name": "South Williamsburg",
    "address": "109 S 5th Street, Brooklyn NY 11249"
  },
  {
    "region": "US",
    "city": "New York City",
    "name": "Madison",
    "address": "261 Madison Avenue, New York NY 10016"
  },
  {
    "region": "US",
    "city": "New York City",
    "name": "85 Broad St",
    "address": "85 Broad St, New York NY 10004"
  },
  {
    "region": "US",
    "city": "New York City",
    "name": "222 Broadway",
    "address": "222 Broadway, New York NY 10038"
  },
  {
    "region": "US",
    "city": "New York City",
    "name": "135 Madison Ave",
    "address": "135 Madison Ave, New York NY 10016"
  },
  {
    "region": "US",
    "city": "Orange County",
    "name": "3200 Park Center Drive",
    "address": "3200 Park Center Drive, Costa Mesa CA 92626"
  },
  {
    "region": "US",
    "city": "Orange County",
    "name": "Spectrum Center",
    "address": "200 Spectrum Center Drive, Irvine CA 92618"
  },
  {
    "region": "US",
    "city": "Philadelphia/DC Suburbs",
    "name": "Tysons",
    "address": "1775 Tysons Blvd, Tysons VA 22102"
  },
  {
    "region": "US",
    "city": "Philadelphia/DC Suburbs",
    "name": "1601 Market",
    "address": "1601 Market Street, Philadelphia PA 19103"
  },
  {
    "region": "US",
    "city": "Philadelphia/DC Suburbs",
    "name": "1900 Market",
    "address": "1900 Market Street, Philadelphia PA 19103"
  },
  {
    "region": "US",
    "city": "Philadelphia/DC Suburbs",
    "name": "Crystal City",
    "address": "2221 South Clark St, Arlington VA 22202"
  },
  {
    "region": "US",
    "city": "Philadelphia/DC Suburbs",
    "name": "Walnut St.",
    "address": "1430 Walnut Street, Philadelphia PA 19102"
  },
  {
    "region": "US",
    "city": "Philadelphia/DC Suburbs",
    "name": "Northern Liberties",
    "address": "1010 N Hancock St, Philadelphia PA 19123"
  },
  {
    "region": "US",
    "city": "Portland",
    "name": "Custom House",
    "address": "220 NW 8th Ave, Portland OR 97209"
  },
  {
    "region": "US",
    "city": "Portland",
    "name": "920 SW 6th Ave",
    "address": "920 SW 6th Ave, Portland OR 97204"
  },
  {
    "region": "US",
    "city": "Portland",
    "name": "Pioneer Place",
    "address": "700 SW Fifth Avenue, Portland OR 97204"
  },
  {
    "region": "US",
    "city": "San Diego",
    "name": "B Street",
    "address": "600 B Street, San Diego CA 92101"
  },
  {
    "region": "US",
    "city": "San Diego",
    "name": "Aventine",
    "address": "8910 University Center Lane, San Diego CA 92122"
  },
  {
    "region": "US",
    "city": "Seattle",
    "name": "Denny Triangle",
    "address": "1099 Stewart Street, Seattle WA 98101"
  },
  {
    "region": "US",
    "city": "Seattle",
    "name": "925 4th Avenue",
    "address": "925 4th Avenue, Seattle WA 98104"
  },
  {
    "region": "US",
    "city": "Seattle",
    "name": "Lincoln Square",
    "address": "10400 NE 4th Street, Bellevue WA 98004"
  },
  {
    "region": "US",
    "city": "Seattle",
    "name": "Holyoke Building",
    "address": "107 Spring St, Seattle WA 98104"
  },
  {
    "region": "US",
    "city": "Seattle",
    "name": "South Lake Union",
    "address": "500 Yale Avenue North, Seattle WA 98109"
  },
  {
    "region": "US",
    "city": "Seattle",
    "name": "Westlake Tower",
    "address": "1601 5th Ave, Seattle WA 98101"
  },
  {
    "region": "US",
    "city": "Seattle",
    "name": "1411 4th Avenue",
    "address": "1411 4th Avenue, Seattle WA 98101"
  },
  {
    "region": "US",
    "city": "Seattle",
    "name": "1600 7th Avenue",
    "address": "1600 7th Avenue, Seattle WA 98191"
  },
  {
    "region": "US",
    "city": "Silicon Valley",
    "name": "401 San Antonio Road",
    "address": "401 San Antonio Road, Mountain View CA 94040"
  },
  {
    "region": "US",
    "city": "Washington DC",
    "name": "Apollo",
    "address": "810 7th Street NE, Washington DC 20002"
  },
  {
    "region": "US",
    "city": "Washington DC",
    "name": "Dupont Circle",
    "address": "1875 Connecticut Ave NW, Washington DC 20009"
  },
  {
    "region": "US",
    "city": "Washington DC",
    "name": "80 M SE",
    "address": "80 M Street SE, Washington DC 20003"
  },
  {
    "region": "US",
    "city": "Washington DC",
    "name": "Manhattan Laundry",
    "address": "1342 Florida Ave NW, Washington DC 20009"
  },
  {
    "region": "US",
    "city": "Washington DC",
    "name": "K Street",
    "address": "1875 K St NW, Washington DC 20006"
  },
  {
    "region": "US",
    "city": "Washington DC",
    "name": "Chinatown",
    "address": "718 7th St NW, Washington DC 20001"
  },
  {
    "region": "US",
    "city": "Washington DC",
    "name": "White House",
    "address": "1440 G St NW, Washington DC 20005"
  },
  {
    "region": "US",
    "city": "Washington DC",
    "name": "Wonder Bread Factory",
    "address": "641 S Street NW, Washington DC 20001"
  }
]